{
  "mass_singlet": {"type": "uniform", "min_value": 100, "max_value": 5000},
  "mass_doublet": {"type": "uniform", "min_value": 100, "max_value": 5000},
  "lambda_S": {"type": "merged",
    "distribution1": {"type": "uniform_exponential", "factor": -1, "base": 10, "min_exponent": -10, "max_exponent": 0},
    "distribution2": {"type": "uniform_exponential", "factor": 1, "base": 10, "min_exponent": -10, "max_exponent": 0}
  },
  "lambda_D": {"type": "merged",
    "distribution1": {"type": "uniform_exponential", "factor": -1, "base": 10, "min_exponent": -10, "max_exponent": 0},
    "distribution2": {"type": "uniform_exponential", "factor": 1, "base": 10, "min_exponent": -10, "max_exponent": 0}
  },
  "lambda_P": {"type": "merged",
    "distribution1": {"type": "uniform_exponential", "factor": -1, "base": 10, "min_exponent": -10, "max_exponent": 0},
    "distribution2": {"type": "uniform_exponential", "factor": 1, "base": 10, "min_exponent": -10, "max_exponent": 0}
  },
  "lambda_PP": {"type": "uniform_exponential", "factor": 1, "base": 10, "min_exponent": -10, "max_exponent": 0},
  "A": {"type": "uniform_exponential", "factor": 1, "base": 10, "min_exponent": -10, "max_exponent": 5}
}